base_parser/.DS_Store
base_parser/__init__.py
base_parser/auth.py
base_parser/base_parser.py
base_parser/config_parser/.DS_Store
base_parser/config_parser/__init__.py
base_parser/config_parser/config.py
base_parser/config_parser/configs/config_example.yaml
base_parser/config_parser/configs/test_config2.yaml
base_parser/config_parser/tests.py
base_parser/json_parsable.py
base_parser/log/__init__.py
base_parser/log/logger.py
base_parser/utils.py
base_parser/vuln.py
base_parser-0.1.45.dist-info/METADATA
base_parser-0.1.45.dist-info/WHEEL
base_parser-0.1.45.dist-info/RECORD
